ct_veegan/__init__.py
ct_veegan/models.py
ct_veegan/trainer.py
ct_veegan/utils.py
ct_veegan/wiki.id.case.finetuned.model
ct_veegan/wrapper.py
ct_veegan-0.2.8.dist-info/METADATA
ct_veegan-0.2.8.dist-info/WHEEL
ct_veegan-0.2.8.dist-info/top_level.txt
ct_veegan-0.2.8.dist-info/RECORD
