Metadata-Version: 2.4
Name: ct_veegan
Version: 0.2.8
Summary: GAN package for sequence vector generation and classification
Home-page: https://github.com/username/ct_veegan
Author: Laode Hidayat
Author-email: your_email@example.com
Classifier: Programming Language :: Python :: 3
Classifier: License :: OSI Approved :: MIT License
Classifier: Operating System :: OS Independent
Requires-Python: >=3.8
Requires-Dist: torch>=2.0.0
Requires-Dist: numpy>=1.20.0
Requires-Dist: requests>=2.0.0
Requires-Dist: scikit-learn>=1.4.2
Requires-Dist: imbalanced-learn>=0.14.0
Requires-Dist: gensim>=4.0.0
Requires-Dist: datasets>=2.0.0
Dynamic: author
Dynamic: author-email
Dynamic: classifier
Dynamic: home-page
Dynamic: requires-dist
Dynamic: requires-python
Dynamic: summary
